odoo/addons/l10n_it_account_balance_eu/README.rst
odoo/addons/l10n_it_account_balance_eu/__init__.py
odoo/addons/l10n_it_account_balance_eu/__manifest__.py
odoo/addons/l10n_it_account_balance_eu/data/account.balance.eu.csv
odoo/addons/l10n_it_account_balance_eu/data/account_balance_eu_reclassification.xml
odoo/addons/l10n_it_account_balance_eu/i18n/it.po
odoo/addons/l10n_it_account_balance_eu/i18n/l10n_it_account_balance_eu.pot
odoo/addons/l10n_it_account_balance_eu/models/__init__.py
odoo/addons/l10n_it_account_balance_eu/models/account_balance_eu.py
odoo/addons/l10n_it_account_balance_eu/readme/CONFIGURE.rst
odoo/addons/l10n_it_account_balance_eu/readme/CONTRIBUTORS.rst
odoo/addons/l10n_it_account_balance_eu/readme/DESCRIPTION.rst
odoo/addons/l10n_it_account_balance_eu/readme/ROADMAP.rst
odoo/addons/l10n_it_account_balance_eu/readme/USAGE.rst
odoo/addons/l10n_it_account_balance_eu/report/__init__.py
odoo/addons/l10n_it_account_balance_eu/report/account_balance_eu_report.py
odoo/addons/l10n_it_account_balance_eu/report/account_balance_eu_report.xml
odoo/addons/l10n_it_account_balance_eu/report/templates/layouts.xml
odoo/addons/l10n_it_account_balance_eu/security/account_balance_eu.xml
odoo/addons/l10n_it_account_balance_eu/static/description/icon.png
odoo/addons/l10n_it_account_balance_eu/static/description/index.html
odoo/addons/l10n_it_account_balance_eu/static/src/css/report.css
odoo/addons/l10n_it_account_balance_eu/static/src/js/action_manager_report.js
odoo/addons/l10n_it_account_balance_eu/static/src/js/client_action.js
odoo/addons/l10n_it_account_balance_eu/static/src/xml/report.xml
odoo/addons/l10n_it_account_balance_eu/tests/__init__.py
odoo/addons/l10n_it_account_balance_eu/tests/test_balance_eu.py
odoo/addons/l10n_it_account_balance_eu/views/account_balance_eu_view.xml
odoo/addons/l10n_it_account_balance_eu/views/report_template.xml
odoo/addons/l10n_it_account_balance_eu/wizards/__init__.py
odoo14_addon_l10n_it_account_balance_eu-14.0.1.0.1.dist-info/METADATA
odoo14_addon_l10n_it_account_balance_eu-14.0.1.0.1.dist-info/WHEEL
odoo14_addon_l10n_it_account_balance_eu-14.0.1.0.1.dist-info/top_level.txt
odoo14_addon_l10n_it_account_balance_eu-14.0.1.0.1.dist-info/RECORD
