Metadata-Version: 2.1
Name: odoo14-addon-l10n-it-account-balance-eu
Version: 14.0.1.0.1
Summary: ITA - Bilancio UE con XBRL
Home-page: https://github.com/OCA/l10n-italy
Author: MKT Srl, Odoo Community Association (OCA)
Author-email: support@odoo-community.org
License: AGPL-3
Platform: UNKNOWN
Classifier: Programming Language :: Python
Classifier: Framework :: Odoo
Classifier: Framework :: Odoo :: 14.0
Classifier: License :: OSI Approved :: GNU Affero General Public License v3
Classifier: Development Status :: 3 - Alpha
Requires-Python: >=3.6
Requires-Dist: odoo14-addon-date-range
Requires-Dist: odoo14-addon-l10n-it-fiscalcode
Requires-Dist: odoo14-addon-l10n-it-rea
Requires-Dist: odoo14-addon-report-xlsx
Requires-Dist: odoo14-addon-report-xml
Requires-Dist: odoo <14.1dev,>=14.0a
